fastHistory/__init__.py
fastHistory/bash/bash-preexec.sh
fastHistory/bash/f.sh
fastHistory/config/__init__.py
fastHistory/config/configReader.py
fastHistory/config/default_fastHistory.conf
fastHistory/config/default_version.txt
fastHistory/config/setupManager.py
fastHistory/console/__init__.py
fastHistory/console/colors.py
fastHistory/console/consoleHelp.py
fastHistory/console/consoleUtils.py
fastHistory/console/loggerBash.py
fastHistory/database/InputData.py
fastHistory/database/__init__.py
fastHistory/database/dataManager.py
fastHistory/database/databaseCommon.py
fastHistory/database/databaseSQLite.py
fastHistory/parser/__init__.py
fastHistory/parser/bashParser.py
fastHistory/parser/inputParser.py
fastHistory/parser/manParser.py
fastHistory/pick/__init__.py
fastHistory/pick/drawer.py
fastHistory/pick/pageEditCommand.py
fastHistory/pick/pageEditDescription.py
fastHistory/pick/pageEditTags.py
fastHistory/pick/pageGeneric.py
fastHistory/pick/pageInfo.py
fastHistory/pick/pageSelect.py
fastHistory/pick/picker.py
fastHistory/pick/textManager.py
fastHistory-2.2.2.dist-info/METADATA
fastHistory-2.2.2.dist-info/WHEEL
fastHistory-2.2.2.dist-info/entry_points.txt
fastHistory-2.2.2.dist-info/top_level.txt
fastHistory-2.2.2.dist-info/RECORD
