Metadata-Version: 2.1
Name: fastHistory
Version: 2.2.2
Summary: A python tool connected to your terminal to store important commands and search them in a new and faster way
Home-page: http://github.com/mkcn/fasthistory
Author: Mirko Conti
Author-email: mirko.conti29@gmail.com
License: GPLv3+
Keywords: bash history search fast
Platform: OS-independent
Classifier: Development Status :: 5 - Production/Stable
Classifier: Intended Audience :: Developers
Classifier: Intended Audience :: System Administrators
Classifier: Intended Audience :: End Users/Desktop
Classifier: Natural Language :: English
Classifier: License :: OSI Approved :: GNU General Public License v3 (GPLv3)
Classifier: Operating System :: OS Independent
Classifier: Programming Language :: Python
Classifier: Programming Language :: Python :: 3
Requires-Dist: bashlex (>=0.15)
Requires-Dist: pyperclip (>=1.8.2)
